[
  {
    "giftId": 5655,
    "giftName": "Rose",
    "image": "https://p16-webcast.tiktokcdn.com/img/maliva/webcast-va/eba3a9bb85c33e017f3648eaf88d7189~tplv-obj.png",
    "diamonds": 1,
    "maxRepeatCount": 50,
    "active": true
  },
  {
    "giftId": 7934,
    "giftName": "Heart Me",
    "image": "https://p16-webcast.tiktokcdn.com/img/maliva/webcast-va/d56945782445b0b8c8658ed44f894c7b~tplv-obj.png",
    "diamonds": 1,
    "maxRepeatCount": 1,
    "active": true
  },
  {
    "giftId": 5658,
    "giftName": "Perfume"
  },
  {
    "giftId": 5269,
    "giftName": "TikTok",
    "image": "https://p16-webcast.tiktokcdn.com/img/maliva/webcast-va/802a21ae29f9fae5abe3693de9f874bd~tplv-obj.png",
    "diamonds": 1,
    "maxRepeatCount": 100,
    "active": true
  },
  {
    "giftId": 15231,
    "giftName": "Love you so much",
    "image": "https://p16-webcast.tiktokcdn.com/img/alisg/webcast-sg/resource/fc549cf1bc61f9c8a1c97ebab68dced7.png~tplv-obj.png",
    "diamonds": 1,
    "maxRepeatCount": 2,
    "active": true
  },
  {
    "giftId": 8825,
    "giftName": "Lucky pig",
    "image": "https://p16-webcast.tiktokcdn.com/img/maliva/webcast-va/resource/d53125bd5416e6f2f6ab61da02ddd302.png~tplv-obj.png",
    "diamonds": 10,
    "maxRepeatCount": 5,
    "active": true
  },
  {
    "giftId": 8913,
    "giftName": "Rosa"
  },
  {
    "giftId": 17465,
    "giftName": "little kisses",
    "image": "https://p16-webcast.tiktokcdn.com/img/alisg/webcast-sg/resource/0a5db92508ee667339289b2f87bc3123.png~tplv-obj.png",
    "diamonds": 20,
    "maxRepeatCount": 1,
    "active": true
  },
  {
    "giftId": 5509,
    "giftName": "Sunglasses"
  },
  {
    "giftId": 5879,
    "giftName": "Doughnut"
  },
  {
    "giftId": 5487,
    "giftName": "Finger Heart",
    "image": "https://p16-webcast.tiktokcdn.com/img/maliva/webcast-va/a4c4dc437fd3a6632aba149769491f49.png~tplv-obj.png",
    "diamonds": 5,
    "maxRepeatCount": 1,
    "active": true
  },
  {
    "giftId": 13651,
    "giftName": "Popular Vote",
    "image": "https://p16-webcast.tiktokcdn.com/img/alisg/webcast-sg/resource/b342e28d73dac6547e0b3e2ad57f6597.png~tplv-obj.png",
    "diamonds": 1,
    "maxRepeatCount": 1,
    "active": true
  },
  {
    "giftId": 6652,
    "giftName": "Autumn 2024"
  },
  {
    "giftId": 5660,
    "giftName": "Hand Heart",
    "image": "https://p16-webcast.tiktokcdn.com/img/maliva/webcast-va/6cd022271dc4669d182cad856384870f~tplv-obj.png",
    "diamonds": 100,
    "maxRepeatCount": 1,
    "active": true
  },
  {
    "giftId": 5586,
    "giftName": "Hearts",
    "image": "https://p16-webcast.tiktokcdn.com/img/maliva/webcast-va/934b5a10dee8376df5870a61d2ea5cb6.png~tplv-obj.png",
    "diamonds": 199,
    "maxRepeatCount": 8,
    "active": true
  },
  {
    "giftId": 6007,
    "giftName": "Boxing Gloves"
  },
  {
    "giftId": 11179,
    "giftName": "Naughty Chicken"
  },
  {
    "giftId": 14397,
    "giftName": "Fairy Wings"
  },
  {
    "giftId": 5585,
    "giftName": "Confetti"
  },
  {
    "giftId": 6781,
    "giftName": "Watermelon Love"
  },
  {
    "giftId": 10138,
    "giftName": "Drip Brewing"
  },
  {
    "giftId": 5827,
    "giftName": "Ice Cream Cone"
  },
  {
    "giftId": 57800,
    "giftName": "Parrot",
    "image": "https://p16-webcast.tiktokcdn.com/img/alisg/webcast-sg/resource/a38efdb71f680c88e9bd14199ff907f2.png~tplv-obj.png",
    "diamonds": 1,
    "maxRepeatCount": 1,
    "active": true
  },
  {
    "giftId": 15232,
    "giftName": "You're awesome",
    "image": "https://p16-webcast.tiktokcdn.com/img/alisg/webcast-sg/resource/e9cafce8279220ed26016a71076d6a8a.png~tplv-obj.png",
    "diamonds": 1,
    "maxRepeatCount": 1,
    "active": true
  },
  {
    "giftId": 16145,
    "giftName": "Summer Solstice",
    "image": "https://p16-webcast.tiktokcdn.com/img/alisg/webcast-sg/resource/0884604db383907f9dd0fe9512937589.png~tplv-obj.png",
    "diamonds": 300,
    "maxRepeatCount": 1,
    "active": true
  },
  {
    "giftId": 57593,
    "giftName": "Hive Escape",
    "image": "https://p16-webcast.tiktokcdn.com/img/alisg/webcast-sg/resource/92bd8c4f0d4fef2cee16e9adcd50a222.png~tplv-obj.png",
    "diamonds": 549,
    "maxRepeatCount": 1,
    "active": true
  },
  {
    "giftId": 5897,
    "giftName": "Swan"
  },
  {
    "giftId": 5659,
    "giftName": "Paper Crane"
  },
  {
    "giftId": 9948,
    "giftName": "You're Amazing"
  },
  {
    "giftId": 37318,
    "giftName": "Monster Vãi Chè"
  },
  {
    "giftId": 6427,
    "giftName": "Hat and Mustache"
  },
  {
    "giftId": 10961,
    "giftName": "Peach",
    "image": "https://p16-webcast.tiktokcdn.com/img/maliva/webcast-va/resource/ff861a220649506452e3dc35c58266ea.png~tplv-obj.png",
    "diamonds": 5,
    "maxRepeatCount": 1,
    "active": true
  },
  {
    "giftId": 7122,
    "giftName": " Gem Gun"
  },
  {
    "giftId": 19448,
    "giftName": "Slow motion"
  },
  {
    "giftId": 17667,
    "giftName": "Side by Side"
  },
  {
    "giftId": 41327,
    "giftName": "Cánh Tiên 1900",
    "image": "https://p16-webcast.tiktokcdn.com/img/alisg/webcast-sg/resource/saliency_seg_1769154345445_0.4aef53e18c5f9db7dbac6a5527d883ab.png~tplv-obj.png",
    "diamonds": 1,
    "maxRepeatCount": 1,
    "active": true
  },
  {
    "giftId": 57597,
    "giftName": "Vocal Bear"
  },
  {
    "giftId": 7412,
    "giftName": "Bing Chiling"
  },
  {
    "giftId": 8635,
    "giftName": "Okay"
  },
  {
    "giftId": 9875,
    "giftName": "Shamrock"
  },
  {
    "giftId": 57596,
    "giftName": "Sax Groove",
    "image": "https://p16-webcast.tiktokcdn.com/img/alisg/webcast-sg/resource/48af771dd2405a0d01b4dd7184e8cfad.png~tplv-obj.png",
    "diamonds": 299,
    "maxRepeatCount": 1,
    "active": true
  },
  {
    "giftId": 13087,
    "giftName": "Bubblegum"
  },
  {
    "giftId": 57327,
    "giftName": "Shining Starlight"
  },
  {
    "giftId": 6064,
    "giftName": "GG"
  },
  {
    "giftId": 17950,
    "giftName": "Candy Puffs"
  },
  {
    "giftId": 17947,
    "giftName": "Bubbly Kiss"
  },
  {
    "giftId": 16690,
    "giftName": "Super Popular"
  },
  {
    "giftId": 17948,
    "giftName": "Bubblegum Kiss"
  },
  {
    "giftId": 17949,
    "giftName": "Candy Kiss"
  }
]